<mythosdtheme>

  <!-- if timeformat is set to 'FROMSETTINGS', it will use the time format
       specified in the general mythtv settings -->
  <timeformat>FROMSETTINGS</timeformat>
  <fadeaway>30</fadeaway>

  <font name="notifyfont">
    <color>200</color>
    <filename>DejaVuSans-Oblique.ttf</filename>
    <size>16</size>
    <size:small>14</size:small>
    <shadow>2,2</shadow>
    <outline>yes</outline>
  </font>

  <font name="notifysmallfont">
    <color>200</color>
    <filename>DejaVuSans-Oblique.ttf</filename>
    <size>12</size>
    <size:small>10</size:small>
    <shadow>2,2</shadow>
    <outline>yes</outline>
  </font>

  <font name="infofont">
    <color>255</color>
    <filename>DejaVuSans.ttf</filename>
    <size>16</size>
    <size:small>12</size:small>
    <shadow>2,2</shadow>
  </font>
  
  <font name="smallinfofont">
    <color>255</color>
    <filename>DejaVuSans.ttf</filename>
    <size>14</size>
    <size:small>12</size:small>
    <shadow>2,2</shadow>
  </font>

   <font name="titlefont">
    <color normal="#ccff00">255</color>
    <filename>DejaVuSans-Oblique.ttf</filename> 
    <size>24</size>
    <size:small>14</size:small>
    <shadow>2,2</shadow>
  </font>

  <font name="smalltitlefont">
    <color normal="#ccff00">255</color>
    <filename>DejaVuSans-Oblique.ttf</filename>
    <size>18</size>
    <size:small>14</size:small>
    <shadow>2,2</shadow>
  </font>

  <font name="grayfont">
    <color>200</color>
    <filename>DejaVuSans-Oblique.ttf</filename> 
    <size>14</size>
    <size:small>12</size:small>
    <outline>yes</outline>
  </font>

  <font name="statusgrayfont">
    <color>200</color>
    <filename>DejaVuSans-Oblique.ttf</filename>
    <size>16</size>
    <size:small>14</size:small>
    <outline>yes</outline>
  </font>

  <font name="infofontgray">
    <color>128</color>
    <filename>DejaVuSans.ttf</filename>
    <size>16</size>
    <size:small>14</size:small>
    <shadow>2,2</shadow>
  </font>

  <font name="largechannelfont">
    <color>255</color>
    <filename>DejaVuSans-Bold.ttf</filename>
    <size>26</size>
    <size:small>22</size:small>
    <shadow>2,2</shadow>
  </font>

  <font name="channelfont">
    <color>255</color>
    <filename>DejaVuSans-Bold.ttf</filename> 
    <size>24</size>
    <size:small>18</size:small>
    <shadow>2,2</shadow>
  </font>

  <font name="callsignfont">
    <color>200</color>
    <filename>DejaVuSans-Bold.ttf</filename>
    <size>14</size>
    <size:small>12</size:small>
    <shadow>2,2</shadow>
  </font>

  <font name="timefont">
    <color>255</color>
    <filename>DejaVuSans.ttf</filename>
    <size>16</size>
    <size:small>14</size:small>
    <shadow>2,2</shadow>
  </font>

  <font name="statustimefont">
    <color>255</color>
    <filename>DejaVuSans.ttf</filename>
    <size>16</size>
    <size:small>14</size:small>
    <shadow>2,2</shadow>
  </font>

  <font name="settings">
    <color>220</color>
    <filename>DejaVuSans.ttf</filename>
    <size>18</size>
    <size:small>16</size:small>
    <shadow>3,3</shadow>
  </font>

  <font name="scroller">
    <color>220</color>
    <filename>DejaVuSans-Bold.ttf</filename>
    <size>18</size>
    <size:small>16</size:small>
    <shadow>3,3</shadow>
  </font>
 
  <container name="channel_number" fademovement="-6,-6">
    <image name="background">
      <filename>osd-small.png</filename>
      <position>40,320</position>
    </image>
    <image name="channelicon">
      <position>45,350</position>
      <staticsize>40,40</staticsize>
    </image>
    <textarea name="channum" align="center">
       <area>160,350,100,30</area>
       <font>largechannelfont</font>
    </textarea>
    <textarea name="callsign" align="center">
       <multiline>yes</multiline>
       <area>160,380,100,60</area>
       <font>callsignfont</font>
    </textarea>
  </container> 
  
  <container name="program_info" fademovement="0,-6">
    <image name="background">
      <filename>osd-bar-mid.png</filename>
      <position>0,30</position>
    </image>
    <textarea name="title">
      <area>100,38,440,35</area>
      <font>titlefont</font>
    </textarea>
    <textarea name="description">
      <multiline>yes</multiline>
      <area>100,95,500,71</area>
      <font>infofont</font>
      <value>%SUBTITLE|"|" %%DESCRIPTION%</value>
    </textarea>
    <textarea name="starttime">
      <area>100,70,450,20</area>
      <font>grayfont</font>
      <value>(%TIMEDATE%)  %LENMINS%</value>
    </textarea>
    <image name="coverart">
      <position>40,35</position>
      <staticsize>40,80</staticsize>
    </image>
    <image name="channelicon">
      <position>40,35</position>
      <staticsize>40,40</staticsize>
    </image>
    <textarea name="channum" align="center">
       <area>25,125,70,30</area>
       <font>channelfont</font>
    </textarea>
    <textarea name="time" align="right">
        <area>485,38,105,45</area>
        <font>statustimefont</font>
     </textarea>
  </container>

  <container name="program_info_small" fademovement="0,-6">
    <image name="background">
      <filename>osd-small.png</filename>
      <position>240,30</position>
      <staticsize>360,120</staticsize>
    </image>
    <textarea name="title" align="center">
      <area>245,75,350,25</area>
      <font>smalltitlefont</font>
    </textarea>
    <textarea name="subtitle" align="center">
      <multiline>yes</multiline>
      <area>245,105,350,40</area>
      <font>smallinfofont</font>
      <value>%SUBTITLE|"|" %</value>
    </textarea>
    <image name="channelicon">
      <position>250,35</position>
      <staticsize>35,35</staticsize>
    </image>
    <textarea name="channum" align="center">
       <area>280,35,80,25</area>
       <font>channelfont</font>
    </textarea>
    <textarea name="callsign" align="left">
       <multiline>yes</multiline>
       <area>370,35,110,45</area>
       <font>callsignfont</font>
    </textarea>
    <textarea name="time" align="right">
        <area>485,38,105,45</area>
        <font>statustimefont</font>
     </textarea>
  </container>

  <container name="browse_info" fademovement="0,-6">
    <image name="background">
      <filename>osd-bar-mid.png</filename>
      <position>0,30</position>
    </image>
    <textarea name="title">
      <area>100,35,440,35</area>
      <font>titlefont</font>
      <value>%TITLE%</value>
    </textarea>
    <textarea name="starttime">
      <area>100,70,440,20</area>
      <font>grayfont</font>
      <value>(%STARTTIME% - %ENDTIME%)  %LENMINS%</value>
    </textarea>
    <textarea name="description">
      <multiline>yes</multiline>
      <area>100,90,500,71</area>
      <font>infofont</font>
      <value>%SUBTITLE|"|" %%DESCRIPTION%</value>
    </textarea>
    <image name="channelicon">
      <position>45,35</position>
      <staticsize>40,40</staticsize>
    </image>
    <textarea name="channum" align="center">
       <area>30,80,60,30</area>
       <font>channelfont</font>
    </textarea>
    <textarea name="callsign" align="center">
       <area>26,110,72,60</area>
       <font>callsignfont</font>
    </textarea>
    <textarea name="time" align="right">
        <area>485,38,105,45</area>
        <font>statustimefont</font>
     </textarea>
  </container>
   
  <container name="status" priority="10" fademovement="6,-6">
    <image name="background">
      <filename>osd-small.png</filename>
      <position>320,30</position>
    </image>
    <textarea name="status">
      <area>330,38,200,45</area>
      <multiline>yes</multiline>
      <font>statusgrayfont</font>
    </textarea>
    <image name="sliderframe">
      <filename>slider_frame.png</filename>
      <position>342,86</position>
      <staticsize>240,24</staticsize>
    </image>
    <slider name="statusslider" type="fill">
      <area>345,88,238,18</area>
      <filename>fill_green.png</filename>
    </slider>
    <textarea name="slidertext" align="center">
      <area>346,120,216,40</area>
      <font>infofont</font>
      <multiline>yes</multiline>
    </textarea>
    <textarea name="time" align="right">
        <area>485,38,105,45</area>
        <font>statustimefont</font>
     </textarea>
  </container>

  <container name="settings" fademovement="6,6">
    <image name="background">
      <filename>osd-small.png</filename>
      <position>320,320</position>
    </image>
    <textarea name="settings" align="center">
      <area>340,350,190,100</area>
      <font>statusgrayfont</font>
    </textarea>
  </container>

  <container name="notify_cid_info" priority="10" fademovement="6,6">
    <image name="background">
      <filename>osd-notify.png</filename>
      <position>280,320</position>
    </image>
    <image name="watermark">
      <filename>phone.png</filename>
      <position>35,375</position>
    </image>
    <textarea name="notify_cid_name" align="left">
      <area>285,370,310,20</area>
      <font>notifyfont</font>
      <multiline>no</multiline>
    </textarea>
    <textarea name="notify_cid_num" align="left">
      <area>285,400,310,20</area>
      <font>notifyfont</font>
      <multiline>no</multiline>
    </textarea>
    <textarea name="notify_cid_dt" align="left">
      <area>285,430,310,20</area>
      <font>notifysmallfont</font>
      <multiline>no</multiline>
    </textarea>
  </container>

  <container name="notify_alert_text" priority="10" fademovement="6,6">
    <image name="background">
      <filename>osd-notify.png</filename>
      <position>280,320</position>
    </image>
    <textarea name="notify_text">
      <area>285,330,310,129</area>
      <font>notifyfont</font>
      <multiline>yes</multiline>
    </textarea>
  </container>

  <container name="news_scroller" priority="20">
    <box name="background">
      <area>0,404,640,40</area>
    </box>
    <textarea name="text_scroll">
      <area>0,410,640,40</area>
      <font>scroller</font>
      <scroller>yes</scroller>
      <scrollmovement>-3,0</scrollmovement>
    </textarea>
  </container>

  <container name="editmode" fademovement="0,6">
    <image name="background">
      <filename>osd-editmode.png</filename>
      <position>55,347</position>
      <staticsize>530,100</staticsize>
    </image>
    <image name="sliderframe">
      <filename>slider_frame.png</filename>
      <position>123,392</position>
      <staticsize>414,25</staticsize>
    </image>
    <textarea name="edit">
      <area>80,355,250,27</area>
      <font>scroller</font>
      <value>Edit</value>
    </textarea>
    <slider name="editslider" type="edit">
      <area>127,394,406,20</area>
      <filename>fill_green.png</filename>
      <altfilename>fill_red.png</altfilename>
    </slider>
    <slider name="editposition" type="position">
      <area>127,391,406,34</area>
      <filename>position_marker.png</filename>
    </slider>
    <editarrow name="left">
      <filename>cut_end.png</filename>
      <area>127,392,406,26</area>
    </editarrow>
    <editarrow name="right">
      <filename>cut_start.png</filename>
      <area>127,392,406,26</area>
    </editarrow>
    <textarea name="timedisplay">
      <area>255,368,200,60</area>
      <font>infofont</font>
    </textarea>
    <textarea name="framedisplay" align="center">
      <area>220,422,200,60</area>
      <font>grayfont</font>
    </textarea>
    <textarea name="cutindicator">
      <area>40,30,100,30</area>
      <font>settings</font>
    </textarea>
    <textarea name="seekamount" align="right">
      <area>440,355,125,40</area>
      <font>statustimefont</font>
    </textarea>
  </container>


 <container name="basedialog" priority="0" fademovement="0,0"> <!-- must be named this --> 
   <image name="background"> 
     <filename>popup.png</filename> 
     <position>68,44</position> 
   </image> 
   <positionimage name="selector"> 
     <filename>selector.png</filename> 
      <position>95,251</position>
      <position>95,281</position> 
      <position>95,311</position> 
      <position>95,341</position> 
      <position>95,371</position> 
    </positionimage> 
   <textarea name="message"> 
      <area>100,70,455,220</area> 
      <font>infofont</font> 
      <multiline>yes</multiline> 
   </textarea> 
   <textarea name="option1"> 
      <area>100,255,455,30</area> 
      <font>infofont</font> 
      <altfont>infofontgray</altfont> 
   </textarea> 
   <textarea name="option2"> 
      <area>100,285,455,30</area> 
      <font>infofont</font> 
      <altfont>infofontgray</altfont> 
   </textarea> 
   <textarea name="option3"> 
      <area>100,315,455,30</area> 
      <font>infofont</font> 
      <altfont>infofontgray</altfont> 
   </textarea> 
   <textarea name="option4"> 
      <area>100,345,455,30</area> 
      <font>infofont</font> 
      <altfont>infofontgray</altfont> 
   </textarea> 
   <textarea name="option5">
      <area>100,375,455,30</area>
      <font>infofont</font>
      <altfont>infofontgray</altfont>
    </textarea>
 </container> 
 
  <container name="menu">
    <listtreemenu name="menu">
      <area>40,40,620,300</area>
      <listsize>0,0,274,260</listsize>
      <leveloffset>10</leveloffset>
      <gradient type="unselected" start="#505050" end="#000000" alpha="150">
      </gradient>
      <gradient type="selected" start="#52CA38" end="#349838" alpha="255">
      </gradient>
      <fcnfont name="infofont" function="active"></fcnfont>
      <fcnfont name="infofontgray" function="inactive"></fcnfont>
    </listtreemenu>
  </container>
 
  <container name="channel_editor">
    <image name="background">
      <filename>osd-channel-edit.png</filename>
      <position>102,99</position>
    </image>
    <textarea name="dialog_label" align="center">
      <area>105,106,450,40</area>
      <font>infofont</font>
      <value>Channel Editor</value>
    </textarea>
    <textarea name="callsign_label" align="right">
      <area>120,151,155,40</area>
      <font>infofont</font>
      <value>Callsign</value>
    </textarea>
    <textarea name="callsign" entry="0">
      <area>310,151,220,40</area>
      <font>infofontgray</font>
      <altfont>infofont</altfont>
      <value></value>
    </textarea>
    <textarea name="channum_label" align="right">
      <area>120,200,155,40</area>
      <font>infofont</font>
      <value>Channel #</value>
    </textarea>
    <textarea name="channum" entry="1">
      <area>310,200,220,40</area>
      <font>infofontgray</font>
      <altfont>infofont</altfont>
      <value></value>
    </textarea>
    <textarea name="channame_label" align="right">
      <area>120,246,155,40</area>
      <font>infofont</font>
      <value>Channel Name</value>
    </textarea>
    <textarea name="channame" entry="2">
      <area>310,246,220,40</area>
      <font>infofontgray</font>
      <altfont>infofont</altfont>
      <value></value>
    </textarea>
    <textarea name="XMLTV_label" align="right">
      <area>120,295,155,40</area>
      <font>infofont</font>
      <value>XMLTV ID</value>
    </textarea>
    <textarea name="XMLTV" entry="3">
      <area>310,295,220,40</area>
      <font>infofontgray</font>
      <altfont>infofont</altfont>
      <value></value>
    </textarea>
    <textarea name="probe_all" entry="4" button="yes" align="center">
      <area>120,342,185,40</area>
      <font>infofontgray</font>
      <altfont>infofont</altfont>
      <value>[P]robe</value>
    </textarea>
    <textarea name="ok" entry="5" button="yes" align="center">
      <area>330,342,185,40</area>
      <font>infofontgray</font>
      <altfont>infofont</altfont>
      <value>[O]k</value>
    </textarea>
  </container>
    
</mythosdtheme>
