<mythuitheme> 

  <window name="backgroundwindow"> 
    <imagetype name="backimg"> 
      <filename>background.png</filename> 
      <staticsize>-1,-1</staticsize> 
    </imagetype> 
 
    <font name="clock" face="Arial"> 
      <color>#FFFFFF</color> 
      <size>22</size> 
      <size:small>18</size:small> 
      <size:big>22</size:big> 
      <bold>yes</bold> 
    </font> 

    <clock name="clock"> 
      <area>10,110,790,50</area> 
      <font>clock</font> 
      <align>center</align> 
      <format>%DATE% %TIME%</format> 
    </clock> 
  </window> 

</mythuitheme> 

