<mythmenu name="SCHEDULE">

   <button>
      <type>TV_PROGRAM_GUIDE</type>
      <text>Program Guide</text>
      <text lang="IT">Guida programmi</text>
      <text lang="ES">Guía de programas</text>
      <text lang="CA">Guia de programes</text>
      <text lang="NL">Programmagids</text>
      <text lang="FR">Grille Horaire</text>
      <text lang="DE">TV Programm</text>
      <text lang="DK">Program Guide</text>
      <text lang="PT">Guia de Programação</text>
      <text lang="SV">Programguide</text>
      <text lang="JA">番組ガイド</text>
      <text lang="SI">Programski vodič</text>
      <text lang="ET">Telekava</text>
      <alttext>Guide</alttext>
      <alttext lang="FR">Grille</alttext>
      <alttext lang="ES">Guía</alttext>
      <alttext lang="CA">Guia</alttext>
      <alttext lang="DE">EPG</alttext>
      <alttext lang="DK">Guide</alttext>
      <alttext lang="NL">Gids</alttext>
      <alttext lang="NL">Guia</alttext>
      <alttext lang="SV">Guide</alttext>
      <alttext lang="JA">ガイド</alttext>
      <alttext lang="SI">Vodič</alttext>
      <alttext lang="ET">Kava</alttext>
      <alttext lang="PT">Guia</alttext>
      <alttext lang="ET">Kava</alttext>
      <action>TV_SCHEDULE</action>
   </button>

   <button>
      <type>TV_PROGFIND</type>
      <text>Program Finder</text>
      <text lang="IT">Ricerca programmi</text>
      <text lang="ES">Buscar Programas</text>
      <text lang="CA">Cercar programes</text>
      <text lang="NL">Programma's Zoeken</text>
      <text lang="FR">Recherche de programmes</text>
      <text lang="DE">Alphabetische Suche</text>
      <text lang="DK">Program Søger</text>
      <text lang="PT">Procurar Programa</text>
      <text lang="SV">Programletaren</text>
      <text lang="JA">番組検索</text>
      <text lang="SI">Iskalec programov</text>
      <text lang="ET">Programmiotsija</text>
      <alttext>Finder</alttext>
      <alttext lang="FR">Recherche</alttext>
      <alttext lang="ES">Buscar</alttext>
      <alttext lang="CA">Cercar</alttext>
      <alttext lang="DE">ABC Suche</alttext>
      <alttext lang="DK">Søger</alttext>
      <alttext lang="NL">Zoeken A-Z</alttext>
      <alttext lang="PT">Procurar</alttext>
      <alttext lang="SV">Letaren</alttext>
      <alttext lang="JA">検索</alttext>
      <alttext lang="SI">Iskalec</alttext>
      <alttext lang="ET">Otsija</alttext>
      <action>TV_PROGFIND</action>
   </button>

   <button>
      <type>TV_SEARCH_LISTINGS</type>
      <text>Search Listings</text>
      <text lang="DE">Suche</text>
      <text lang="FR">Recherche</text>
      <text lang="SV">Sök i TV-tablå</text>
      <text lang="NL">Gids Doorzoeken</text>
      <text lang="JA">リスト検索</text>
      <text lang="SI">Iskanje seznamov</text>
      <text lang="DK">Søg på lister</text>
      <text lang="PT">Pesquisar Listagens</text>
      <text lang="ET">Kavade otsing</text>
      <text lang="ES">Buscar Listados</text>
      <alttext>Search</alttext>
      <alttext lang="SV">Sök tablå</alttext>
      <alttext lang="NL">Zoeken Gids</alttext>      
      <alttext lang="SI">Iskanje</alttext>
      <alttext lang="DK">Lister</alttext>
      <alttext lang="PT">Pesquisar</alttext>
      <alttext lang="ET">Otsing</alttext>
      <action>MENU tv_search.xml</action>
   </button>

<!--
   <button>
      <type>TV_SCHEDULE</type>
      <text>Instant Recording</text>
      <text lang="IT">Registrazione manuale</text>
      <text lang="ES">Grabación Instanánea</text>
      <text lang="CA">Gravar ara</text>
      <text lang="NL">Instant Opname</text>
      <text lang="FR">Enregistrement manuel</text>
      <text lang="DE">Sofortige Aufnahme</text>
      <text lang="DK">Optag lige nu</text>
      <text lang="PT">Gravação Imediata</text>
      <text lang="SV">Omedelbar inspelning</text>
      <text lang="JA">簡単録画</text>
      <text lang="ET">Kohene salvestamine</text>
      <alttext>Instant Record</alttext>
      <alttext lang="FR">Enreg. manuel</alttext>
      <alttext lang="ES">Grab. inst.</alttext>
      <alttext lang="CA">Grav. inst.</alttext>
      <alttext lang="DK">Optag nu</alttext>
      <alttext lang="NL">Instant</alttext>
      <alttext lang="PT">Gravação Imediata</alttext>
      <alttext lang="SV">Omedelbar</alttext>
      <alttext lang="JA">簡単録画</alttext>
      <alttext lang="ET">Kohene salvestamine</alttext>
      <action>TV_MANUAL</action>
   </button>
-->

   <button>
      <type>TV_CUSTOM_RECORD</type>
      <text>Custom Record</text>
      <text lang="FR">Personnalisé</text>
      <text lang="SV">Avancerad</text>
      <text lang="JA">カスタム録画</text>
      <text lang="DE">freie Planung</text>
      <text lang="SI">Poljubno snemanje</text>
      <text lang="ET">Kohandatud salvestamine</text>
      <text lang="PT">Regras de Gravação</text>
      <text lang="ES">Avanzada</text>
      <text lang="NL">Geavanceerde Opname</text>
      <text lang="DK">Avanceret</text>
      <action>TV_CUSTOM_RECORD</action>
   </button>

   <button>
      <type>TV_MANUAL_SCHEDULE</type>
      <text>Manual Schedule</text>
      <text lang="ES">Programación Manual</text>
      <text lang="CA">Programar Gravacions</text>
      <text lang="DE">Manuelle Aufnahme</text>
      <text lang="FR">Manuel</text>
      <text lang="DK">Manuel programmering</text>
      <text lang="NL">Manuele Opname</text>
      <text lang="PT">Gravação Manual</text>
      <text lang="SV">Manuell schemaläggning</text>
      <text lang="JA">手動予約</text>
      <text lang="SI">Ročno snemanje</text>
      <text lang="ET">Käsitsi salvestamine</text>
      <alttext>Man. Sched.</alttext>
      <alttext lang="ES">Manual</alttext>
      <alttext lang="CA">Programar</alttext>
      <alttext lang="DE">Manuell</alttext>
      <alttext lang="DK">Manuel prog.</alttext>
      <alttext lang="NL">Manueel</alttext>
      <alttext lang="PT">Manual</alttext>
      <alttext lang="SV">Manuell</alttext>
      <alttext lang="JA">手動</alttext>
      <alttext lang="SI">Ročno</alttext>
      <alttext lang="ET">Käsitsi</alttext>
      <action>TV_MANUALSCHEDULE</action>
   </button>

   <button>
      <type>TV_RECPRIORITIES</type>
      <text>Recording Priorities</text>
      <text lang="DE">Aufnahmeprioritäten</text>
      <text lang="FR">Priorités d'enregistrement</text>
      <text lang="NL">Opnameprioriteiten</text>      
      <text lang="SV">Inspelningsprioriteter</text>
      <text lang="JA">録画優先順位</text>
      <text lang="SI">Snemalne prioritete</text>
      <text lang="PT">Prioridades de Gravação</text>
      <text lang="ET">Salvestamisprioriteedid</text>
      <text lang="ES">Prioridades Grabación</text>
      <alttext>Priorities</alttext>
      <alttext lang="SV">Prioriteter</alttext>
      <alttext lang="NL">Prioriteiten</alttext>
      <alttext lang="DE">Prioritäten</alttext>
      <alttext lang="SI">Prioritete</alttext>
      <alttext lang="PT">Prioridades</alttext>
      <alttext lang="ET">Prioriteedid</alttext>
      <alttext lang="ES">Prioridades</alttext>
      <action>TV_SET_RECPRIORITIES</action>
   </button>

   <button>
      <type>TV_CONFLICTS</type>
      <text>Upcoming Recordings</text>
      <text lang="IT">Correggi i conflitti</text>
      <text lang="FR">Conflicts</text>
      <text lang="ES">Resolver conflictos</text>
      <text lang="CA">Resoldre Conflictes</text>
      <text lang="NL">Geplande Opnames</text>
      <text lang="FR">Gestion des conflits</text>
      <text lang="DE">Aufnahmeplan</text>
      <text lang="DK">Løs konflikter</text>
      <text lang="PT">Resolver Conflitos</text>
      <text lang="SV">Kommande inspelningar</text>
      <text lang="JA">これからの録画</text>
      <text lang="FI">Tulevat Nauhoitukset</text>
      <text lang="ZH_TW">修正預設錄影衝突</text>
      <text lang="SI">Prihajajoča snemanja</text>
      <text lang="ET">Tulevased salvestamised</text>
      <alttext lang="SV">Kommande</alttext>
      <alttext lang="ET">Tulevased</alttext>
      <alttext lang="ES">Conflictos</alttext>
      <action>TV_FIX_CONFLICTS</action>
   </button>

</mythmenu>
